pypubtrack/VERSION
pypubtrack/__init__.py
pypubtrack/authentication.py
pypubtrack/cli.py
pypubtrack/config.py
pypubtrack/endpoint.py
pypubtrack/pypubtrack.py
pypubtrack/util.py
pypubtrack/templates/config.toml
pypubtrack/templates/publication.j2
pypubtrack-0.3.0.dist-info/AUTHORS.rst
pypubtrack-0.3.0.dist-info/LICENSE
pypubtrack-0.3.0.dist-info/METADATA
pypubtrack-0.3.0.dist-info/WHEEL
pypubtrack-0.3.0.dist-info/entry_points.txt
pypubtrack-0.3.0.dist-info/top_level.txt
pypubtrack-0.3.0.dist-info/RECORD
