Metadata-Version: 2.1
Name: pypubtrack
Version: 0.3.0
Summary: A python client for the pubtrack REST api
Home-page: https://github.com/the16thpythonist/pypubtrack
Author: Jonas Teufel
Author-email: jonseb1998@gmail.com
License: MIT license
Keywords: pypubtrack
Platform: UNKNOWN
Classifier: Development Status :: 2 - Pre-Alpha
Classifier: Intended Audience :: Developers
Classifier: License :: OSI Approved :: MIT License
Classifier: Natural Language :: English
Classifier: Programming Language :: Python :: 3
Classifier: Programming Language :: Python :: 3.5
Classifier: Programming Language :: Python :: 3.6
Classifier: Programming Language :: Python :: 3.7
Classifier: Programming Language :: Python :: 3.8
Requires-Python: >=3.5
Requires-Dist: Click (>=7.0)
Requires-Dist: jinja2 (>=2.11.2)
Requires-Dist: pybliometrics (>=2.6.2)
Requires-Dist: pykitopen (>=0.1.0)
